{"version": 0.6, "generator": "Overpass API 0.7.62.8 e802775f", "osm3s": {"timestamp_osm_base": "2025-11-14T09:26:01Z", "copyright": "The data included in this document is from www.openstreetmap.org. The data is made available under ODbL."}, "elements": [{"type": "node", "id": 459658064, "lat": 47.0721531, "lon": 6.8685742}, {"type": "node", "id": 459658065, "lat": 47.0720487, "lon": 6.8686231}, {"type": "node", "id": 459658066, "lat": 47.0720732, "lon": 6.8687356}, {"type": "node", "id": 459658067, "lat": 47.0721776, "lon": 6.8686867}, {"type": "node", "id": 459658068, "lat": 47.0731252, "lon": 6.8705206}, {"type": "node", "id": 459658069, "lat": 47.0728728, "lon": 6.8700314}, {"type": "node", "id": 459658070, "lat": 47.07274, "lon": 6.8701785}, {"type": "node", "id": 459658071, "lat": 47.0729453, "lon": 6.8705775}, {"type": "node", "id": 459658072, "lat": 47.0728911, "lon": 6.8706711}, {"type": "node", "id": 459658073, "lat": 47.072927, "lon": 6.8707407}, {"type": "node", "id": 459658074, "lat": 47.0731078, "lon": 6.8699123}, {"type": "node", "id": 459658075, "lat": 47.0730445, "lon": 6.869777}, {"type": "node", "id": 459658076, "lat": 47.0729351, "lon": 6.8698874}, {"type": "node", "id": 459658077, "lat": 47.0729984, "lon": 6.8700226}, {"type": "node", "id": 459658078, "lat": 47.0727618, "lon": 6.8689194}, {"type": "node", "id": 459658079, "lat": 47.0726806, "lon": 6.8690059}, {"type": "node", "id": 459658080, "lat": 47.0727548, "lon": 6.8691561}, {"type": "node", "id": 459658081, "lat": 47.0726995, "lon": 6.869215}, {"type": "node", "id": 459658083, "lat": 47.07273, "lon": 6.8692768}, {"type": "node", "id": 459658084, "lat": 47.0725829, "lon": 6.8694336}, {"type": "node", "id": 459658085, "lat": 47.0726509, "lon": 6.8695712}, {"type": "node", "id": 459658086, "lat": 47.0729397, "lon": 6.8692793}, {"type": "node", "id": 459658087, "lat": 47.0722718, "lon": 6.8692007}, {"type": "node", "id": 459658088, "lat": 47.0721985, "lon": 6.8692781}, {"type": "node", "id": 459658089, "lat": 47.0723598, "lon": 6.869607}, {"type": "node", "id": 459658090, "lat": 47.0724295, "lon": 6.8695334}, {"type": "node", "id": 459658091, "lat": 47.072412, "lon": 6.8694976}, {"type": "node", "id": 459658092, "lat": 47.0725465, "lon": 6.8693554}, {"type": "node", "id": 459658093, "lat": 47.0724518, "lon": 6.8691623}, {"type": "node", "id": 459658094, "lat": 47.0723209, "lon": 6.8693007}, {"type": "node", "id": 538783609, "lat": 47.0745643, "lon": 6.868813}, {"type": "node", "id": 538783610, "lat": 47.0744676, "lon": 6.8688585}, {"type": "node", "id": 538783611, "lat": 47.0744315, "lon": 6.868693}, {"type": "node", "id": 538783612, "lat": 47.0745283, "lon": 6.8686475}, {"type": "node", "id": 538783613, "lat": 47.0745132, "lon": 6.868497}, {"type": "node", "id": 538783614, "lat": 47.0744451, "lon": 6.8685584}, {"type": "node", "id": 538783615, "lat": 47.0743892, "lon": 6.8684247}, {"type": "node", "id": 538783616, "lat": 47.0744573, "lon": 6.8683633}, {"type": "node", "id": 538784006, "lat": 47.073966, "lon": 6.8716395}, {"type": "node", "id": 538784007, "lat": 47.073859, "lon": 6.871629}, {"type": "node", "id": 538784008, "lat": 47.0738481, "lon": 6.8718684}, {"type": "node", "id": 538784009, "lat": 47.0739184, "lon": 6.8718753}, {"type": "node", "id": 538784010, "lat": 47.0739227, "lon": 6.8717821}, {"type": "node", "id": 538784011, "lat": 47.0739594, "lon": 6.8717857}, {"type": "node", "id": 538784012, "lat": 47.074068, "lon": 6.8719077}, {"type": "node", "id": 538784013, "lat": 47.0740294, "lon": 6.8719135}, {"type": "node", "id": 538784014, "lat": 47.0740353, "lon": 6.8719992}, {"type": "node", "id": 538784015, "lat": 47.0739862, "lon": 6.8720065}, {"type": "node", "id": 538784016, "lat": 47.0740006, "lon": 6.8722134}, {"type": "node", "id": 538784017, "lat": 47.0740884, "lon": 6.8722002}, {"type": "node", "id": 538784018, "lat": 47.0732491, "lon": 6.8721457}, {"type": "node", "id": 538784019, "lat": 47.0731625, "lon": 6.8721641}, {"type": "node", "id": 538784020, "lat": 47.0731849, "lon": 6.8723916}, {"type": "node", "id": 538784021, "lat": 47.0732715, "lon": 6.8723732}, {"type": "node", "id": 538784022, "lat": 47.0731369, "lon": 6.8728488}, {"type": "node", "id": 538784023, "lat": 47.0730963, "lon": 6.8728937}, {"type": "node", "id": 538784024, "lat": 47.0730273, "lon": 6.8727589}, {"type": "node", "id": 538784025, "lat": 47.073068, "lon": 6.872714}, {"type": "node", "id": 538784026, "lat": 47.0739382, "lon": 6.8741389}, {"type": "node", "id": 538784027, "lat": 47.0738458, "lon": 6.8741905}, {"type": "node", "id": 538784028, "lat": 47.073814, "lon": 6.8740679}, {"type": "node", "id": 538784029, "lat": 47.0739063, "lon": 6.8740162}, {"type": "node", "id": 538784030, "lat": 47.0726494, "lon": 6.8733635}, {"type": "node", "id": 538784031, "lat": 47.0725812, "lon": 6.8734354}, {"type": "node", "id": 538784032, "lat": 47.0725088, "lon": 6.8732873}, {"type": "node", "id": 538784033, "lat": 47.0725769, "lon": 6.8732154}, {"type": "node", "id": 538784034, "lat": 47.0726893, "lon": 6.8737243}, {"type": "node", "id": 538784035, "lat": 47.0726026, "lon": 6.8737097}, {"type": "node", "id": 538784036, "lat": 47.072593, "lon": 6.8738325}, {"type": "node", "id": 538784037, "lat": 47.0726797, "lon": 6.8738471}, {"type": "node", "id": 538784038, "lat": 47.0723249, "lon": 6.8741131}, {"type": "node", "id": 538784039, "lat": 47.0722416, "lon": 6.8740991}, {"type": "node", "id": 538784040, "lat": 47.0722259, "lon": 6.8743007}, {"type": "node", "id": 538784041, "lat": 47.0723092, "lon": 6.8743146}, {"type": "node", "id": 538784042, "lat": 47.0723159, "lon": 6.8744177}, {"type": "node", "id": 538784043, "lat": 47.0722351, "lon": 6.8744057}, {"type": "node", "id": 538784044, "lat": 47.072221, "lon": 6.8746111}, {"type": "node", "id": 538784045, "lat": 47.0723017, "lon": 6.8746231}, {"type": "node", "id": 538784046, "lat": 47.0723198, "lon": 6.8747646}, {"type": "node", "id": 538784047, "lat": 47.0722537, "lon": 6.8747487}, {"type": "node", "id": 538784048, "lat": 47.0722324, "lon": 6.8749407}, {"type": "node", "id": 538784049, "lat": 47.0722985, "lon": 6.8749565}, {"type": "node", "id": 538784050, "lat": 47.0723132, "lon": 6.8750797}, {"type": "node", "id": 538784051, "lat": 47.0722338, "lon": 6.875064}, {"type": "node", "id": 538784052, "lat": 47.0722166, "lon": 6.8752507}, {"type": "node", "id": 538784053, "lat": 47.0722961, "lon": 6.8752665}, {"type": "node", "id": 538784054, "lat": 47.0727184, "lon": 6.8747105}, {"type": "node", "id": 538784055, "lat": 47.0726634, "lon": 6.8747296}, {"type": "node", "id": 538784056, "lat": 47.07267, "lon": 6.8747703}, {"type": "node", "id": 538784057, "lat": 47.0726371, "lon": 6.8747817}, {"type": "node", "id": 538784058, "lat": 47.0726586, "lon": 6.874915}, {"type": "node", "id": 538784059, "lat": 47.0727704, "lon": 6.874876}, {"type": "node", "id": 538784060, "lat": 47.0727528, "lon": 6.8747669}, {"type": "node", "id": 538784061, "lat": 47.0727288, "lon": 6.8747752}, {"type": "node", "id": 538784062, "lat": 47.0727481, "lon": 6.8751103}, {"type": "node", "id": 538784063, "lat": 47.0726724, "lon": 6.8751402}, {"type": "node", "id": 538784064, "lat": 47.0727121, "lon": 6.8753573}, {"type": "node", "id": 538784065, "lat": 47.0727878, "lon": 6.8753275}, {"type": "node", "id": 538784066, "lat": 47.0742149, "lon": 6.8738751}, {"type": "node", "id": 538784067, "lat": 47.0741449, "lon": 6.8738941}, {"type": "node", "id": 538784068, "lat": 47.0741624, "lon": 6.8740328}, {"type": "node", "id": 538784069, "lat": 47.0742323, "lon": 6.8740138}, {"type": "node", "id": 538784070, "lat": 47.0748172, "lon": 6.8741548}, {"type": "node", "id": 538784071, "lat": 47.0747305, "lon": 6.8741625}, {"type": "node", "id": 538784072, "lat": 47.0747368, "lon": 6.8743173}, {"type": "node", "id": 538784073, "lat": 47.0748235, "lon": 6.8743096}, {"type": "node", "id": 538784074, "lat": 47.0749215, "lon": 6.8748478}, {"type": "node", "id": 538784075, "lat": 47.0748382, "lon": 6.8748869}, {"type": "node", "id": 538784076, "lat": 47.0748101, "lon": 6.8747577}, {"type": "node", "id": 538784077, "lat": 47.0748934, "lon": 6.8747186}, {"type": "node", "id": 538784078, "lat": 47.073877, "lon": 6.8750298}, {"type": "node", "id": 538784079, "lat": 47.0738177, "lon": 6.8749733}, {"type": "node", "id": 538784080, "lat": 47.0737858, "lon": 6.8750454}, {"type": "node", "id": 538784081, "lat": 47.0738451, "lon": 6.8751019}, {"type": "node", "id": 538784082, "lat": 47.0750707, "lon": 6.8751661}, {"type": "node", "id": 538784083, "lat": 47.0749869, "lon": 6.8751763}, {"type": "node", "id": 538784084, "lat": 47.074999, "lon": 6.8753895}, {"type": "node", "id": 538784085, "lat": 47.0750827, "lon": 6.8753793}, {"type": "node", "id": 538784086, "lat": 47.0750828, "lon": 6.8755471}, {"type": "node", "id": 538784087, "lat": 47.0750184, "lon": 6.8755721}, {"type": "node", "id": 538784088, "lat": 47.0750416, "lon": 6.8757006}, {"type": "node", "id": 538784089, "lat": 47.075106, "lon": 6.8756756}, {"type": "node", "id": 538784090, "lat": 47.0751887, "lon": 6.8758629}, {"type": "node", "id": 538784091, "lat": 47.0750367, "lon": 6.8759145}, {"type": "node", "id": 538784092, "lat": 47.0750686, "lon": 6.8761168}, {"type": "node", "id": 538784093, "lat": 47.0751629, "lon": 6.8760847}, {"type": "node", "id": 538784094, "lat": 47.0751527, "lon": 6.8760202}, {"type": "node", "id": 538784095, "lat": 47.0752104, "lon": 6.8760007}, {"type": "node", "id": 599598266, "lat": 47.0693922, "lon": 6.8746262}, {"type": "node", "id": 599598267, "lat": 47.0702163, "lon": 6.8724041}, {"type": "node", "id": 599598268, "lat": 47.070234, "lon": 6.8725099}, {"type": "node", "id": 599598269, "lat": 47.0702469, "lon": 6.8723272}, {"type": "node", "id": 599598270, "lat": 47.0702568, "lon": 6.8724388}, {"type": "node", "id": 599598271, "lat": 47.0702874, "lon": 6.8723619}, {"type": "node", "id": 599598272, "lat": 47.0702676, "lon": 6.8724116}, {"type": "node", "id": 599598273, "lat": 47.0703339, "lon": 6.8725843}, {"type": "node", "id": 599598275, "lat": 47.0703678, "lon": 6.8724863}, {"type": "node", "id": 599598276, "lat": 47.0707003, "lon": 6.8723971}, {"type": "node", "id": 599598277, "lat": 47.0706177, "lon": 6.8724351}, {"type": "node", "id": 599598278, "lat": 47.0707481, "lon": 6.8726207}, {"type": "node", "id": 599598279, "lat": 47.0708243, "lon": 6.8725446}, {"type": "node", "id": 599598282, "lat": 47.0706655, "lon": 6.8726587}, {"type": "node", "id": 599598283, "lat": 47.0708712, "lon": 6.8727313}, {"type": "node", "id": 599598284, "lat": 47.0708974, "lon": 6.8730517}, {"type": "node", "id": 599598285, "lat": 47.0709202, "lon": 6.873267}, {"type": "node", "id": 599598286, "lat": 47.0702257, "lon": 6.873563}, {"type": "node", "id": 599598287, "lat": 47.0701438, "lon": 6.8736841}, {"type": "node", "id": 599598288, "lat": 47.0701967, "lon": 6.8737612}, {"type": "node", "id": 599598289, "lat": 47.070069, "lon": 6.8739884}, {"type": "node", "id": 599598290, "lat": 47.0700066, "lon": 6.8740721}, {"type": "node", "id": 599598291, "lat": 47.0700623, "lon": 6.8741617}, {"type": "node", "id": 599598292, "lat": 47.0701247, "lon": 6.8740781}, {"type": "node", "id": 599598293, "lat": 47.0702786, "lon": 6.8736401}, {"type": "node", "id": 599598294, "lat": 47.0703312, "lon": 6.8740199}, {"type": "node", "id": 599598295, "lat": 47.0702923, "lon": 6.8740484}, {"type": "node", "id": 599598296, "lat": 47.0703281, "lon": 6.8741534}, {"type": "node", "id": 599598297, "lat": 47.0703669, "lon": 6.8741249}, {"type": "node", "id": 599598298, "lat": 47.0692908, "lon": 6.8747035}, {"type": "node", "id": 599598300, "lat": 47.0693542, "lon": 6.8748826}, {"type": "node", "id": 599598301, "lat": 47.0694556, "lon": 6.8748053}, {"type": "node", "id": 599598302, "lat": 47.0710339, "lon": 6.872431}, {"type": "node", "id": 599598303, "lat": 47.0710272, "lon": 6.8726468}, {"type": "node", "id": 599598304, "lat": 47.0710401, "lon": 6.8726983}, {"type": "node", "id": 599598305, "lat": 47.0710938, "lon": 6.8726692}, {"type": "node", "id": 599598306, "lat": 47.0710586, "lon": 6.8730148}, {"type": "node", "id": 599598307, "lat": 47.0710814, "lon": 6.8732301}, {"type": "node", "id": 599598308, "lat": 47.0716078, "lon": 6.8728133}, {"type": "node", "id": 599598309, "lat": 47.0716798, "lon": 6.8727385}, {"type": "node", "id": 599598310, "lat": 47.0716948, "lon": 6.8729938}, {"type": "node", "id": 599598311, "lat": 47.0717668, "lon": 6.8729191}, {"type": "node", "id": 599598312, "lat": 47.0719503, "lon": 6.8727777}, {"type": "node", "id": 599598313, "lat": 47.0718701, "lon": 6.8729446}, {"type": "node", "id": 599598314, "lat": 47.0719597, "lon": 6.8730373}, {"type": "node", "id": 599598315, "lat": 47.0720399, "lon": 6.8728704}, {"type": "node", "id": 599598316, "lat": 47.0721241, "lon": 6.8730174}, {"type": "node", "id": 599598317, "lat": 47.0720342, "lon": 6.8730891}, {"type": "node", "id": 599598318, "lat": 47.0720898, "lon": 6.8732397}, {"type": "node", "id": 599598319, "lat": 47.0721798, "lon": 6.8731681}, {"type": "node", "id": 599598320, "lat": 47.0722224, "lon": 6.8732213}, {"type": "node", "id": 599598321, "lat": 47.0721473, "lon": 6.8732879}, {"type": "node", "id": 599598322, "lat": 47.072204, "lon": 6.8734258}, {"type": "node", "id": 599598324, "lat": 47.0722791, "lon": 6.8733592}, {"type": "node", "id": 649577358, "lat": 47.0680596, "lon": 6.875486}, {"type": "node", "id": 649577362, "lat": 47.0681388, "lon": 6.8757157}, {"type": "node", "id": 649577364, "lat": 47.0678395, "lon": 6.8760252}, {"type": "node", "id": 649577365, "lat": 47.0677804, "lon": 6.876077}, {"type": "node", "id": 649577367, "lat": 47.0678315, "lon": 6.8762028}, {"type": "node", "id": 649577369, "lat": 47.0678907, "lon": 6.876151}, {"type": "node", "id": 649577374, "lat": 47.0677917, "lon": 6.8763662}, {"type": "node", "id": 649577376, "lat": 47.0676928, "lon": 6.8764634}, {"type": "node", "id": 649577378, "lat": 47.0677709, "lon": 6.8766349}, {"type": "node", "id": 649577379, "lat": 47.0678699, "lon": 6.8765377}, {"type": "node", "id": 649577385, "lat": 47.0682984, "lon": 6.8755971}, {"type": "node", "id": 649577388, "lat": 47.0682786, "lon": 6.8755395}, {"type": "node", "id": 649577393, "lat": 47.0682426, "lon": 6.8755662}, {"type": "node", "id": 649577395, "lat": 47.0681833, "lon": 6.8753942}, {"type": "node", "id": 649577397, "lat": 47.0682242, "lon": 6.8759287}, {"type": "node", "id": 649577400, "lat": 47.068356, "lon": 6.8758881}, {"type": "node", "id": 649577402, "lat": 47.0683295, "lon": 6.875703}, {"type": "node", "id": 649577403, "lat": 47.0681978, "lon": 6.8757436}, {"type": "node", "id": 649577405, "lat": 47.0684327, "lon": 6.8757179}, {"type": "node", "id": 649577407, "lat": 47.0684819, "lon": 6.8758413}, {"type": "node", "id": 649577409, "lat": 47.0684845, "lon": 6.8756733}, {"type": "node", "id": 649577411, "lat": 47.0685338, "lon": 6.8757967}, {"type": "node", "id": 649577414, "lat": 47.0685799, "lon": 6.8759317}, {"type": "node", "id": 649577415, "lat": 47.0685231, "lon": 6.8759864}, {"type": "node", "id": 649577417, "lat": 47.0686281, "lon": 6.8760396}, {"type": "node", "id": 649577419, "lat": 47.0693177, "lon": 6.8749649}, {"type": "node", "id": 649577421, "lat": 47.0692635, "lon": 6.8750092}, {"type": "node", "id": 649577427, "lat": 47.0692952, "lon": 6.8750926}, {"type": "node", "id": 649577429, "lat": 47.0693494, "lon": 6.8750483}, {"type": "node", "id": 649577432, "lat": 47.0691384, "lon": 6.8750793}, {"type": "node", "id": 649577433, "lat": 47.0690594, "lon": 6.8751417}, {"type": "node", "id": 649577435, "lat": 47.0691273, "lon": 6.8753271}, {"type": "node", "id": 649577436, "lat": 47.0692063, "lon": 6.8752647}, {"type": "node", "id": 649577438, "lat": 47.0685713, "lon": 6.8760943}, {"type": "node", "id": 649595920, "lat": 47.0715366, "lon": 6.8745543}, {"type": "node", "id": 649595923, "lat": 47.0714609, "lon": 6.8746206}, {"type": "node", "id": 649595926, "lat": 47.0715833, "lon": 6.8746693}, {"type": "node", "id": 649595929, "lat": 47.0715076, "lon": 6.8747356}, {"type": "node", "id": 849324223, "lat": 47.0719197, "lon": 6.8695672}, {"type": "node", "id": 849324232, "lat": 47.0721016, "lon": 6.8695671}, {"type": "node", "id": 849324233, "lat": 47.0720927, "lon": 6.8693664}, {"type": "node", "id": 849325209, "lat": 47.0718211, "lon": 6.8707529}, {"type": "node", "id": 849325213, "lat": 47.0718956, "lon": 6.8707768}, {"type": "node", "id": 849325221, "lat": 47.0719058, "lon": 6.8707084}, {"type": "node", "id": 849325227, "lat": 47.0718313, "lon": 6.8706846}, {"type": "node", "id": 1175524879, "lat": 47.0730453, "lon": 6.8752358}, {"type": "node", "id": 1175524905, "lat": 47.0731326, "lon": 6.8752185}, {"type": "node", "id": 1175524910, "lat": 47.0730536, "lon": 6.8753272}, {"type": "node", "id": 1175524917, "lat": 47.073141, "lon": 6.87531}, {"type": "node", "id": 1175548603, "lat": 47.0665629, "lon": 6.874415}, {"type": "node", "id": 1175548608, "lat": 47.067221, "lon": 6.8713937}, {"type": "node", "id": 1175548638, "lat": 47.0712491, "lon": 6.872785}, {"type": "node", "id": 1175548647, "lat": 47.0702985, "lon": 6.8676773}, {"type": "node", "id": 1175548706, "lat": 47.0720916, "lon": 6.8729043}, {"type": "node", "id": 1175548748, "lat": 47.067163, "lon": 6.8713479}, {"type": "node", "id": 1175548761, "lat": 47.0722207, "lon": 6.8731947}, {"type": "node", "id": 1175548825, "lat": 47.0707367, "lon": 6.8677483}, {"type": "node", "id": 1175548832, "lat": 47.072219, "lon": 6.8731064}, {"type": "node", "id": 1175548899, "lat": 47.0712303, "lon": 6.8727219}, {"type": "node", "id": 1175548903, "lat": 47.0667182, "lon": 6.8744551}, {"type": "node", "id": 1175548906, "lat": 47.0703225, "lon": 6.8677879}, {"type": "node", "id": 1175548981, "lat": 47.0721167, "lon": 6.8729422}, {"type": "node", "id": 1175549055, "lat": 47.0757432, "lon": 6.8684265}, {"type": "node", "id": 1175549060, "lat": 47.0671801, "lon": 6.8714158}, {"type": "node", "id": 1175549102, "lat": 47.0702393, "lon": 6.867705}, {"type": "node", "id": 1175549155, "lat": 47.067204, "lon": 6.8713257}, {"type": "node", "id": 1175549163, "lat": 47.0720681, "lon": 6.8729377}, {"type": "node", "id": 1175549216, "lat": 47.0707978, "lon": 6.8675904}, {"type": "node", "id": 1175549221, "lat": 47.0757724, "lon": 6.8688055}, {"type": "node", "id": 1175549251, "lat": 47.0666659, "lon": 6.8745447}, {"type": "node", "id": 1175549272, "lat": 47.0713102, "lon": 6.8727458}, {"type": "node", "id": 1175549395, "lat": 47.0666151, "lon": 6.8743255}, {"type": "node", "id": 1175549399, "lat": 47.0702633, "lon": 6.8678156}, {"type": "node", "id": 1175549437, "lat": 47.0722497, "lon": 6.8731441}, {"type": "node", "id": 1175549442, "lat": 47.0720932, "lon": 6.8729756}, {"type": "node", "id": 1175549456, "lat": 47.0708282, "lon": 6.8676851}, {"type": "node", "id": 1175549492, "lat": 47.0756346, "lon": 6.8686763}, {"type": "node", "id": 1175549536, "lat": 47.0712915, "lon": 6.8726827}, {"type": "node", "id": 1175549556, "lat": 47.075881, "lon": 6.8685557}, {"type": "node", "id": 1175549582, "lat": 47.0721901, "lon": 6.873157}, {"type": "node", "id": 1175549592, "lat": 47.0707063, "lon": 6.8676536}, {"type": "node", "id": 1278549357, "lat": 47.0698277, "lon": 6.8642167}, {"type": "node", "id": 1278549417, "lat": 47.0719459, "lon": 6.8661716}, {"type": "node", "id": 1278549439, "lat": 47.0719831, "lon": 6.8660975}, {"type": "node", "id": 1278549470, "lat": 47.0698067, "lon": 6.8643185}, {"type": "node", "id": 1278549474, "lat": 47.071943, "lon": 6.866054}, {"type": "node", "id": 1278549491, "lat": 47.0697029, "lon": 6.8642723}, {"type": "node", "id": 1278549539, "lat": 47.0697239, "lon": 6.8641705}, {"type": "node", "id": 1278550119, "lat": 47.0719058, "lon": 6.8661281}, {"type": "node", "id": 1304617071, "lat": 47.0744294, "lon": 6.8726787}, {"type": "node", "id": 1304617081, "lat": 47.0743429, "lon": 6.8725829}, {"type": "node", "id": 1304617085, "lat": 47.0743882, "lon": 6.8725513}, {"type": "node", "id": 1304617202, "lat": 47.0743842, "lon": 6.8727103}, {"type": "node", "id": 1557485603, "lat": 47.074103, "lon": 6.8673311}, {"type": "node", "id": 1557485604, "lat": 47.0741483, "lon": 6.8671905}, {"type": "node", "id": 1557485605, "lat": 47.07416, "lon": 6.8673708}, {"type": "node", "id": 1557485606, "lat": 47.0742054, "lon": 6.8672303}, {"type": "node", "id": 1647509930, "lat": 47.0701784, "lon": 6.8722232}, {"type": "node", "id": 1647509932, "lat": 47.0701994, "lon": 6.872256}, {"type": "node", "id": 1647509941, "lat": 47.070228, "lon": 6.8721548}, {"type": "node", "id": 1647509945, "lat": 47.070249, "lon": 6.8721877}, {"type": "node", "id": 1647509979, "lat": 47.0709031, "lon": 6.872798}, {"type": "node", "id": 1647509982, "lat": 47.0709204, "lon": 6.8728583}, {"type": "node", "id": 1647509986, "lat": 47.0709435, "lon": 6.8727731}, {"type": "node", "id": 1647509989, "lat": 47.0709608, "lon": 6.8728333}, {"type": "node", "id": 2650555599, "lat": 47.0730376, "lon": 6.8692788}, {"type": "node", "id": 2650555600, "lat": 47.0730499, "lon": 6.8693384}, {"type": "node", "id": 2650555601, "lat": 47.0731093, "lon": 6.8692468}, {"type": "node", "id": 2650555602, "lat": 47.0731217, "lon": 6.8693064}, {"type": "node", "id": 9609322384, "lat": 47.0729097, "lon": 6.8705088}, {"type": "node", "id": 9609322385, "lat": 47.0719333, "lon": 6.8708175}, {"type": "node", "id": 9609322390, "lat": 47.0718939, "lon": 6.8707995}, {"type": "node", "id": 9609322396, "lat": 47.0718831, "lon": 6.8708505}, {"type": "node", "id": 9609322403, "lat": 47.0719225, "lon": 6.8708685}, {"type": "node", "id": 9609322408, "lat": 47.0730425, "lon": 6.8703617}, {"type": "node", "id": 9612525966, "lat": 47.0719701, "lon": 6.8696782}, {"type": "node", "id": 9612525967, "lat": 47.0719962, "lon": 6.8696819}, {"type": "node", "id": 9612525969, "lat": 47.0722331, "lon": 6.8695995}, {"type": "node", "id": 9612525970, "lat": 47.0722496, "lon": 6.869584}, {"type": "node", "id": 9612525971, "lat": 47.0722592, "lon": 6.8695034}, {"type": "node", "id": 9612525972, "lat": 47.0721505, "lon": 6.8694672}, {"type": "node", "id": 10594114215, "lat": 47.069057, "lon": 6.8746915}, {"type": "node", "id": 10594114216, "lat": 47.0690904, "lon": 6.8747872}, {"type": "node", "id": 10594114217, "lat": 47.0690856, "lon": 6.8747907}, {"type": "node", "id": 10594114218, "lat": 47.0690948, "lon": 6.8748199}, {"type": "node", "id": 10594114219, "lat": 47.0690566, "lon": 6.8748473}, {"type": "node", "id": 10594114220, "lat": 47.0690494, "lon": 6.8748246}, {"type": "node", "id": 10594114221, "lat": 47.0690371, "lon": 6.8748316}, {"type": "node", "id": 10594114222, "lat": 47.0690009, "lon": 6.8747323}, {"type": "node", "id": 10594114223, "lat": 47.0693161, "lon": 6.8751218}, {"type": "node", "id": 10594114224, "lat": 47.0693397, "lon": 6.8751717}, {"type": "node", "id": 10594114225, "lat": 47.0692944, "lon": 6.8752196}, {"type": "node", "id": 10594114226, "lat": 47.0692696, "lon": 6.8751691}, {"type": "node", "id": 10594114227, "lat": 47.0695619, "lon": 6.8742992}, {"type": "node", "id": 10594114228, "lat": 47.0696062, "lon": 6.8744204}, {"type": "node", "id": 10594114229, "lat": 47.0695534, "lon": 6.8744615}, {"type": "node", "id": 10594114230, "lat": 47.06951, "lon": 6.8743416}, {"type": "node", "id": 10594114231, "lat": 47.069482, "lon": 6.8745}, {"type": "node", "id": 10594114232, "lat": 47.0695031, "lon": 6.8745624}, {"type": "node", "id": 10594114233, "lat": 47.0695742, "lon": 6.8745044}, {"type": "node", "id": 10594114234, "lat": 47.0695586, "lon": 6.8744575}, {"type": "node", "id": 10594114235, "lat": 47.0695485, "lon": 6.8744479}, {"type": "node", "id": 11415007541, "lat": 47.0729449, "lon": 6.8706114}, {"type": "node", "id": 11415143671, "lat": 47.0728557, "lon": 6.8693688}, {"type": "node", "id": 11415143674, "lat": 47.0727869, "lon": 6.869393}, {"type": "node", "id": 11415143675, "lat": 47.0727976, "lon": 6.8694148}, {"type": "node", "id": 11415143679, "lat": 47.0728398, "lon": 6.8693366}, {"type": "way", "id": 38763167, "nodes": [459658064, 459658065, 459658066, 459658067, 459658064], "tags": {"amenity": "place_of_worship", "building": "chapel", "check_date": "2024-08-31", "name": "Chapelle universelle", "religion": "christian", "source": "Orthophotos2006sitn50cm"}}, {"type": "way", "id": 38763168, "nodes": [459658068, 9609322408, 459658069, 459658070, 9609322384, 459658071, 11415007541, 459658072, 459658073, 459658068], "tags": {"addr:city": "La Vue-des-Alpes", "addr:housenumber": "2", "addr:postcode": "2052", "addr:street": "Route de la Vue-des-Alpes", "amenity": "restaurant", "beds": "90", "building": "yes", "name": "H\u00f4tel de la Vue des Alpes", "rooms": "30", "tourism": "hotel", "website": "http://www.vue-des-alpes.ch/"}}, {"type": "way", "id": 38763169, "nodes": [459658074, 459658075, 459658076, 459658077, 459658074], "tags": {"addr:city": "La Vue-des-Alpes", "addr:housenumber": "4", "addr:postcode": "2052", "addr:street": "Route de la Vue-des-Alpes", "building": "yes", "information": "office", "name": "La vue des Alpes", "phone": "+41 32 889 68 86", "source": "Orthophotos2006sitn50cm", "tourism": "information"}}, {"type": "way", "id": 38763170, "nodes": [459658078, 459658079, 459658080, 459658081, 459658083, 459658084, 459658085, 11415143675, 11415143674, 11415143679, 11415143671, 459658086, 459658078], "tags": {"addr:city": "La Vue-des-Alpes", "addr:housenumber": "9", "addr:postcode": "2052", "addr:street": "Route de la Vue-des-Alpes", "building": "yes", "source": "Orthophotos2006sitn50cm"}}, {"type": "way", "id": 38763171, "nodes": [459658087, 459658088, 459658089, 459658090, 459658091, 459658092, 459658093, 459658094, 459658087], "tags": {"addr:city": "La Vue-des-Alpes", "addr:housenumber": "7", "addr:postcode": "2052", "addr:street": "Route de la Vue-des-Alpes", "building": "yes", "source": "Orthophotos2006sitn50cm"}}, {"type": "way", "id": 43010186, "nodes": [538783609, 538783610, 538783611, 538783612, 538783609], "tags": {"building": "yes", "source": "Orthophotos2006sitn50cm"}}, {"type": "way", "id": 43010187, "nodes": [538783613, 538783614, 538783615, 538783616, 538783613], "tags": {"building": "yes", "source": "Orthophotos2006sitn50cm"}}, {"type": "way", "id": 43010224, "nodes": [538784006, 538784007, 538784008, 538784009, 538784010, 538784011, 538784006], "tags": {"building": "yes", "source": "Orthophotos2006sitn50cm"}}, {"type": "way", "id": 43010225, "nodes": [538784012, 538784013, 538784014, 538784015, 538784016, 538784017, 538784012], "tags": {"addr:city": "La Vue-des-Alpes", "addr:housenumber": "1", "addr:postcode": "2052", "addr:street": "Chemin du Rep\u00e8re", "building": "yes", "source": "Orthophotos2006sitn50cm"}}, {"type": "way", "id": 43010226, "nodes": [538784018, 538784019, 538784020, 538784021, 538784018], "tags": {"addr:city": "La Vue-des-Alpes", "addr:housenumber": "2", "addr:postcode": "2052", "addr:street": "Chemin du Rep\u00e8re", "building": "yes", "source": "Orthophotos2006sitn50cm"}}, {"type": "way", "id": 43010227, "nodes": [538784022, 538784023, 538784024, 538784025, 538784022], "tags": {"addr:city": "La Vue-des-Alpes", "addr:housenumber": "1", "addr:postcode": "2052", "addr:street": "Impasse du Berger", "building": "yes", "source": "Orthophotos2006sitn50cm"}}, {"type": "way", "id": 43010228, "nodes": [538784026, 538784027, 538784028, 538784029, 538784026], "tags": {"addr:city": "La Vue-des-Alpes", "addr:housenumber": "2", "addr:postcode": "2052", "addr:street": "Impasse du Berger", "building": "yes", "source": "Orthophotos2006sitn50cm"}}, {"type": "way", "id": 43010229, "nodes": [538784030, 538784031, 538784032, 538784033, 538784030], "tags": {"addr:city": "La Vue-des-Alpes", "addr:housenumber": "11", "addr:postcode": "2052", "addr:street": "Route des Loges", "building": "yes", "source": "Orthophotos2006sitn50cm"}}, {"type": "way", "id": 43010230, "nodes": [538784034, 538784035, 538784036, 538784037, 538784034], "tags": {"building": "yes", "source": "Orthophotos2006sitn50cm"}}, {"type": "way", "id": 43010231, "nodes": [538784038, 538784039, 538784040, 538784041, 538784038], "tags": {"addr:city": "La Vue-des-Alpes", "addr:housenumber": "2", "addr:postcode": "2052", "addr:street": "Chemin de l'Aurore", "building": "yes", "source": "Orthophotos2006sitn50cm"}}, {"type": "way", "id": 43010232, "nodes": [538784042, 538784043, 538784044, 538784045, 538784042], "tags": {"addr:city": "La Vue-des-Alpes", "addr:housenumber": "4", "addr:postcode": "2052", "addr:street": "Chemin de l'Aurore", "building": "yes", "source": "Orthophotos2006sitn50cm"}}, {"type": "way", "id": 43010233, "nodes": [538784046, 538784047, 538784048, 538784049, 538784046], "tags": {"addr:city": "La Vue-des-Alpes", "addr:housenumber": "6", "addr:postcode": "2052", "addr:street": "Chemin de l'Aurore", "building": "yes", "source": "Orthophotos2006sitn50cm"}}, {"type": "way", "id": 43010234, "nodes": [538784050, 538784051, 538784052, 538784053, 538784050], "tags": {"addr:city": "La Vue-des-Alpes", "addr:housenumber": "8", "addr:postcode": "2052", "addr:street": "Chemin de l'Aurore", "building": "yes", "source": "Orthophotos2006sitn50cm"}}, {"type": "way", "id": 43010235, "nodes": [538784054, 538784055, 538784056, 538784057, 538784058, 538784059, 538784060, 538784061, 538784054], "tags": {"addr:city": "La Vue-des-Alpes", "addr:housenumber": "2", "addr:postcode": "2052", "addr:street": "Passage du Parc", "building": "yes", "source": "Orthophotos2006sitn50cm"}}, {"type": "way", "id": 43010236, "nodes": [538784062, 538784063, 538784064, 538784065, 538784062], "tags": {"addr:city": "La Vue-des-Alpes", "addr:housenumber": "4", "addr:postcode": "2052", "addr:street": "Passage du Parc", "building": "yes", "source": "Orthophotos2006sitn50cm"}}, {"type": "way", "id": 43010237, "nodes": [538784066, 538784067, 538784068, 538784069, 538784066], "tags": {"addr:city": "La Vue-des-Alpes", "addr:housenumber": "4", "addr:postcode": "2052", "addr:street": "Impasse du Berger", "building": "yes", "source": "Orthophotos2006sitn50cm"}}, {"type": "way", "id": 43010238, "nodes": [538784070, 538784071, 538784072, 538784073, 538784070], "tags": {"addr:city": "La Vue-des-Alpes", "addr:housename": "La Giboul\u00e9e", "addr:housenumber": "4", "addr:postcode": "2052", "addr:street": "Chemin du Rep\u00e8re", "building": "yes", "source": "Orthophotos2006sitn50cm"}}, {"type": "way", "id": 43010239, "nodes": [538784074, 538784075, 538784076, 538784077, 538784074], "tags": {"addr:city": "La Vue-des-Alpes", "addr:housename": "les arales", "addr:housenumber": "6", "addr:postcode": "2052", "addr:street": "Chemin du Rep\u00e8re", "building": "yes", "source": "Orthophotos2006sitn50cm"}}, {"type": "way", "id": 43010240, "nodes": [538784078, 538784079, 538784080, 538784081, 538784078], "tags": {"building": "yes", "source": "Orthophotos2006sitn50cm"}}, {"type": "way", "id": 43010241, "nodes": [538784082, 538784083, 538784084, 538784085, 538784082], "tags": {"addr:city": "La Vue-des-Alpes", "addr:housenumber": "8", "addr:postcode": "2052", "addr:street": "Chemin du Rep\u00e8re", "building": "yes", "source": "Orthophotos2006sitn50cm"}}, {"type": "way", "id": 43010242, "nodes": [538784086, 538784087, 538784088, 538784089, 538784086], "tags": {"addr:city": "La Vue-des-Alpes", "addr:housenumber": "10", "addr:postcode": "2052", "addr:street": "Chemin du Rep\u00e8re", "building": "yes", "source": "Orthophotos2006sitn50cm"}}, {"type": "way", "id": 43010243, "nodes": [538784090, 538784091, 538784092, 538784093, 538784094, 538784095, 538784090], "tags": {"addr:city": "La Vue-des-Alpes", "addr:housenumber": "12", "addr:postcode": "2052", "addr:street": "Chemin du Rep\u00e8re", "building": "yes", "source": "Orthophotos2006sitn50cm"}}, {"type": "way", "id": 46991799, "nodes": [599598302, 599598279, 599598283, 599598303, 599598304, 599598305, 599598302], "tags": {"addr:city": "La Vue-des-Alpes", "addr:housenumber": "20", "addr:postcode": "2052", "addr:street": "Route des Loges", "amenity": "restaurant", "building": "yes", "cuisine": "regional", "name": "La P'tite Ferme", "phone": "+41 79 606 41 06", "source": "Orthophotos2006sitn50cm"}}, {"type": "way", "id": 46991800, "nodes": [599598306, 599598284, 599598285, 599598307, 599598306], "tags": {"addr:city": "La Vue-des-Alpes", "addr:housenumber": "18", "addr:postcode": "2052", "addr:street": "Route des Loges", "building": "yes", "source": "Orthophotos2006sitn50cm"}}, {"type": "way", "id": 46991801, "nodes": [599598276, 599598277, 599598282, 599598278, 599598276], "tags": {"addr:city": "La Vue-des-Alpes", "addr:housenumber": "3", "addr:postcode": "2052", "addr:street": "Route des Loges", "building": "yes", "source": "Orthophotos2006sitn50cm"}}, {"type": "way", "id": 46991802, "nodes": [599598269, 599598267, 599598270, 599598272, 599598271, 599598269], "tags": {"building": "yes", "source": "Orthophotos2006sitn50cm"}}, {"type": "way", "id": 46991803, "nodes": [599598272, 599598268, 599598273, 599598275, 599598272], "tags": {"building": "yes", "source": "Orthophotos2006sitn50cm"}}, {"type": "way", "id": 46991804, "nodes": [599598286, 599598287, 599598288, 599598293, 599598286], "tags": {"building": "yes", "source": "Orthophotos2006sitn50cm"}}, {"type": "way", "id": 46991805, "nodes": [599598289, 599598290, 599598291, 599598292, 599598289], "tags": {"building": "yes", "source": "Orthophotos2006sitn50cm"}}, {"type": "way", "id": 46991806, "nodes": [599598294, 599598295, 599598296, 599598297, 599598294], "tags": {"addr:city": "La Vue-des-Alpes", "addr:housenumber": "16", "addr:postcode": "2052", "addr:street": "Route des Loges", "building": "yes", "source": "Orthophotos2006sitn50cm"}}, {"type": "way", "id": 46991807, "nodes": [599598266, 599598298, 599598300, 599598301, 599598266], "tags": {"addr:city": "La Vue-des-Alpes", "addr:housenumber": "14", "addr:postcode": "2052", "addr:street": "Route des Loges", "building": "yes", "source": "Orthophotos2006sitn50cm"}}, {"type": "way", "id": 46991808, "nodes": [599598309, 599598308, 599598310, 599598311, 599598309], "tags": {"building": "yes", "source": "Orthophotos2006sitn50cm"}}, {"type": "way", "id": 46991809, "nodes": [599598312, 599598313, 599598314, 599598315, 599598312], "tags": {"addr:city": "La Vue-des-Alpes", "addr:housenumber": "5", "addr:postcode": "2052", "addr:street": "Route des Loges", "building": "yes", "source": "Orthophotos2006sitn50cm"}}, {"type": "way", "id": 46991810, "nodes": [599598316, 599598317, 599598318, 599598319, 599598316], "tags": {"addr:city": "La Vue-des-Alpes", "addr:housenumber": "7", "addr:postcode": "2052", "addr:street": "Route des Loges", "building": "yes", "source": "Orthophotos2006sitn50cm"}}, {"type": "way", "id": 46991811, "nodes": [599598320, 599598321, 599598322, 599598324, 599598320], "tags": {"addr:city": "La Vue-des-Alpes", "addr:housenumber": "9", "addr:postcode": "2052", "addr:street": "Route des Loges", "building": "yes", "source": "Orthophotos2006sitn50cm"}}, {"type": "way", "id": 50940497, "nodes": [649577419, 649577421, 649577427, 649577429, 649577419], "tags": {"building": "yes", "source": "Orthophotos2006sitn50cm"}}, {"type": "way", "id": 50940498, "nodes": [649577432, 649577433, 649577435, 649577436, 649577432], "tags": {"addr:city": "La Vue-des-Alpes", "addr:housenumber": "12", "addr:postcode": "2052", "addr:street": "Route des Loges", "building": "yes", "source": "Orthophotos2006sitn50cm"}}, {"type": "way", "id": 50940499, "nodes": [649577395, 649577358, 649577362, 649577385, 649577388, 649577393, 649577395], "tags": {"addr:city": "La Vue-des-Alpes", "addr:housenumber": "4", "addr:postcode": "2052", "addr:street": "Route des Loges", "building": "yes", "source": "Orthophotos2006sitn50cm"}}, {"type": "way", "id": 50940500, "nodes": [649577397, 649577400, 649577402, 649577403, 649577397], "tags": {"addr:city": "La Vue-des-Alpes", "addr:housenumber": "6", "addr:postcode": "2052", "addr:street": "Route des Loges", "building": "yes", "source": "Orthophotos2006sitn50cm"}}, {"type": "way", "id": 50940501, "nodes": [649577405, 649577407, 649577411, 649577409, 649577405], "tags": {"addr:city": "La Vue-des-Alpes", "addr:housenumber": "8", "addr:postcode": "2052", "addr:street": "Route des Loges", "building": "yes", "source": "Orthophotos2006sitn50cm"}}, {"type": "way", "id": 50940502, "nodes": [649577414, 649577415, 649577438, 649577417, 649577414], "tags": {"addr:city": "La Vue-des-Alpes", "addr:housenumber": "10", "addr:postcode": "2052", "addr:street": "Route des Loges", "building": "yes", "source": "Orthophotos2006sitn50cm"}}, {"type": "way", "id": 50940503, "nodes": [649577364, 649577365, 649577367, 649577369, 649577364], "tags": {"building": "yes", "source": "Orthophotos2006sitn50cm"}}, {"type": "way", "id": 50940504, "nodes": [649577374, 649577376, 649577378, 649577379, 649577374], "tags": {"addr:city": "La Vue-des-Alpes", "addr:housenumber": "2", "addr:postcode": "2052", "addr:street": "Route des Loges", "building": "yes", "source": "Orthophotos2006sitn50cm"}}, {"type": "way", "id": 50942904, "nodes": [649595920, 649595923, 649595929, 649595926, 649595920], "tags": {"building": "yes", "source": "Orthophotos2006sitn50cm"}}, {"type": "way", "id": 71376733, "nodes": [849324232, 9612525969, 9612525970, 9612525971, 9612525972, 849324233, 849324223, 9612525966, 9612525967, 849324232], "tags": {"building": "yes"}}, {"type": "way", "id": 71376807, "nodes": [849325221, 849325213, 849325209, 849325227, 849325221], "tags": {"building": "shed"}}, {"type": "way", "id": 101822552, "nodes": [1175524917, 1175524905, 1175524879, 1175524910, 1175524917], "tags": {"building": "yes", "source": "Orthophotos2006sitn50cm"}}, {"type": "way", "id": 101824125, "nodes": [1175549216, 1175549456, 1175548825, 1175549592, 1175549216], "tags": {"building": "yes", "source": "Orthophotos2006sitn50cm"}}, {"type": "way", "id": 101824132, "nodes": [1175548832, 1175549437, 1175548761, 1175549582, 1175548832], "tags": {"building": "yes", "source": "Orthophotos2006sitn50cm"}}, {"type": "way", "id": 101824138, "nodes": [1175549556, 1175549055, 1175549492, 1175549221, 1175549556], "tags": {"addr:city": "La Vue-des-Alpes", "addr:housenumber": "52", "addr:postcode": "2052", "addr:street": "Chemin du Pr\u00e9 Raguel", "building": "yes", "source": "Orthophotos2006sitn50cm"}}, {"type": "way", "id": 101824139, "nodes": [1175548706, 1175548981, 1175549442, 1175549163, 1175548706], "tags": {"building": "yes", "source": "Orthophotos2006sitn50cm"}}, {"type": "way", "id": 101824144, "nodes": [1175548647, 1175548906, 1175549399, 1175549102, 1175548647], "tags": {"building": "yes", "source": "Orthophotos2006sitn50cm"}}, {"type": "way", "id": 101824148, "nodes": [1175548903, 1175549251, 1175548603, 1175549395, 1175548903], "tags": {"building": "yes", "source": "Orthophotos2006sitn50cm"}}, {"type": "way", "id": 101824152, "nodes": [1175549272, 1175549536, 1175548899, 1175548638, 1175549272], "tags": {"building": "yes", "source": "Orthophotos2006sitn50cm"}}, {"type": "way", "id": 101824157, "nodes": [1175549155, 1175548608, 1175549060, 1175548748, 1175549155], "tags": {"building": "yes", "source": "Orthophotos2006sitn50cm"}}, {"type": "way", "id": 112506223, "nodes": [1278549474, 1278549439, 1278549417, 1278550119, 1278549474], "tags": {"building": "yes"}}, {"type": "way", "id": 112506226, "nodes": [1278549539, 1278549357, 1278549470, 1278549491, 1278549539], "tags": {"building": "yes"}}, {"type": "way", "id": 115481069, "nodes": [1304617085, 1304617071, 1304617202, 1304617081, 1304617085], "tags": {"addr:city": "La Vue-des-Alpes", "addr:housenumber": "3", "addr:postcode": "2052", "addr:street": "Chemin du Rep\u00e8re", "building": "yes", "name": "Chalet des amis de la montagne"}}, {"type": "way", "id": 142301243, "nodes": [1557485606, 1557485605, 1557485603, 1557485604, 1557485606], "tags": {"building": "yes", "description": "Centre nordique"}}, {"type": "way", "id": 151910024, "nodes": [1647509986, 1647509979, 1647509982, 1647509989, 1647509986], "tags": {"building": "yes", "source": "Orthophotos2006sitn50cm"}}, {"type": "way", "id": 151910025, "nodes": [1647509945, 1647509941, 1647509930, 1647509932, 1647509945], "tags": {"building": "yes", "source": "Orthophotos2006sitn50cm"}}, {"type": "way", "id": 259620198, "nodes": [2650555602, 2650555601, 2650555599, 2650555600, 2650555602], "tags": {"building": "yes", "source": "Orthophotos 2006 SITN 50cm"}}, {"type": "way", "id": 1044298581, "nodes": [9609322396, 9609322390, 9609322385, 9609322403, 9609322396], "tags": {"attraction": "summer_toboggan", "building": "shed", "name": "Tobbogan G\u00e9ant", "phone": "+41 79 349 51 78", "shop": "ticket", "tourism": "attraction", "website": "https://www.toboggans.ch/"}}, {"type": "way", "id": 1136457875, "nodes": [10594114215, 10594114216, 10594114217, 10594114218, 10594114219, 10594114220, 10594114221, 10594114222, 10594114215], "tags": {"building": "yes"}}, {"type": "way", "id": 1136457876, "nodes": [10594114223, 10594114224, 10594114225, 10594114226, 10594114223], "tags": {"building": "yes"}}, {"type": "way", "id": 1136457877, "nodes": [10594114227, 10594114228, 10594114234, 10594114229, 10594114235, 10594114230, 10594114227], "tags": {"building": "yes"}}, {"type": "way", "id": 1136457878, "nodes": [10594114231, 10594114232, 10594114233, 10594114234, 10594114229, 10594114235, 10594114231], "tags": {"building": "yes"}}]}