{"version": 0.6, "generator": "Overpass API 0.7.62.8 e802775f", "osm3s": {"timestamp_osm_base": "2025-11-13T06:24:15Z", "copyright": "The data included in this document is from www.openstreetmap.org. The data is made available under ODbL."}, "elements": [{"type": "node", "id": 459657942, "lat": 47.0325091, "lon": 6.8277775}, {"type": "node", "id": 459657943, "lat": 47.0323312, "lon": 6.8278637}, {"type": "node", "id": 459657944, "lat": 47.0323768, "lon": 6.8280666}, {"type": "node", "id": 459657945, "lat": 47.0325548, "lon": 6.8279804}, {"type": "node", "id": 1278549270, "lat": 47.0323346, "lon": 6.8277977}, {"type": "node", "id": 1278549451, "lat": 47.0323092, "lon": 6.8278743}, {"type": "node", "id": 1278549480, "lat": 47.0323476, "lon": 6.8278557}, {"type": "node", "id": 1278549699, "lat": 47.0322962, "lon": 6.8278163}, {"type": "node", "id": 1329952361, "lat": 47.0330284, "lon": 6.8362613}, {"type": "node", "id": 1329952431, "lat": 47.0330428, "lon": 6.8361342}, {"type": "node", "id": 1329952459, "lat": 47.0331488, "lon": 6.8362907}, {"type": "node", "id": 1329952547, "lat": 47.0331632, "lon": 6.8361635}, {"type": "way", "id": 38763153, "nodes": [459657942, 1278549480, 459657943, 459657944, 459657945, 459657942], "tags": {"amenity": "biergarten", "building": "yes", "name": "Buvette des Pradi\u00e8res-desus", "url": "www.mont-racine.ch"}}, {"type": "way", "id": 112506233, "nodes": [1278549480, 459657943, 1278549451, 1278549699, 1278549270, 1278549480], "tags": {"building": "yes"}}, {"type": "way", "id": 118217243, "nodes": [1329952547, 1329952459, 1329952361, 1329952431, 1329952547], "tags": {"building": "yes", "source": "Orthophotos 2006 SITN 50cm"}}]}